odoo8_addon_website_event_share-8.0.1.0.0-py2.7-nspkg.pth
odoo_addons/website_event_share/__openerp__.py
odoo_addons/website_event_share/__init__.py
odoo_addons/website_event_share/README.rst
odoo_addons/website_event_share/views/website_event.xml
odoo_addons/website_event_share/static/description/icon.png
odoo8_addon_website_event_share-8.0.1.0.0.dist-info/top_level.txt
odoo8_addon_website_event_share-8.0.1.0.0.dist-info/WHEEL
odoo8_addon_website_event_share-8.0.1.0.0.dist-info/RECORD
odoo8_addon_website_event_share-8.0.1.0.0.dist-info/metadata.json
odoo8_addon_website_event_share-8.0.1.0.0.dist-info/DESCRIPTION.rst
odoo8_addon_website_event_share-8.0.1.0.0.dist-info/METADATA
odoo8_addon_website_event_share-8.0.1.0.0.dist-info/namespace_packages.txt
